automatic_spectral_acquisition/__init__.py
automatic_spectral_acquisition/arduino.py
automatic_spectral_acquisition/arduino_adc.py
automatic_spectral_acquisition/calibration.py
automatic_spectral_acquisition/cli.py
automatic_spectral_acquisition/config.py
automatic_spectral_acquisition/constants.py
automatic_spectral_acquisition/core.py
automatic_spectral_acquisition/extras.py
automatic_spectral_acquisition/file_manager.py
automatic_spectral_acquisition/helper.py
automatic_spectral_acquisition/main.py
automatic_spectral_acquisition/oscilloscope.py
automatic_spectral_acquisition-0.2.1.dist-info/entry_points.txt
automatic_spectral_acquisition-0.2.1.dist-info/METADATA
automatic_spectral_acquisition-0.2.1.dist-info/WHEEL
automatic_spectral_acquisition-0.2.1.dist-info/RECORD
