Metadata-Version: 2.1
Name: automatic-spectral-acquisition
Version: 0.2.1
Summary: Python interface for the automatic data acquisition of spectral data.
Author: HugoG16
Author-email: hugo.c.gomes@tecnico.ulisboa.pt
Requires-Python: >=3.12,<4.0
Classifier: Programming Language :: Python :: 3
Classifier: Programming Language :: Python :: 3.12
Requires-Dist: PyVISA (>=1.14.1,<2.0.0)
Requires-Dist: matplotlib (>=3.9.2,<4.0.0)
Requires-Dist: numpy (>=2.0.1,<3.0.0)
Requires-Dist: pydot (>=3.0.1,<4.0.0)
Requires-Dist: pyinputplus (>=0.2.12,<0.3.0)
Requires-Dist: pyserial (>=3.5,<4.0)
Requires-Dist: python-statemachine (>=2.3.4,<3.0.0)
Requires-Dist: rich (>=13.7.1,<14.0.0)
Requires-Dist: typer (>=0.12.4,<0.13.0)
Project-URL: Repository, https://github.com/HugoG16/automatic-spectral-acquisition
